{
  "swagger": "2.0",
  "info": {
    "version": "1.0.0",
    "title": "Asocanitas: API",
    "description": "Documentation automatically generated by the <b>swagger-autogen</b> module.<br>Karen Pabón"
  },
  "host": "http://asocanitas.herokuapp.com/",
  "basePath": "/",
  "tags": [
    {
      "name": "User",
      "description": "Endpoints"
    }
  ],
  "schemes": [
    "http",
    "https"
  ],
  "securityDefinitions": {
    "apiKeyAuth": {
      "type": "apiKey",
      "in": "header",
      "name": "X-API-KEY",
      "description": "any description..."
    }
  },
  "consumes": [
    "application/json"
  ],
  "produces": [
    "application/json"
  ],
  "paths": {
    "/user/": {
      "post": {
        "tags": [],
        "description": "",
        "parameters": [],
        "responses": {
          "201": {
            "description": "Created"
          }
        }
      },
      "get": {
        "tags": [],
        "description": "",
        "parameters": [],
        "responses": {
          "201": {
            "description": "Created"
          },
          "401": {
            "description": "Unauthorized"
          }
        }
      }
    },
    "/user/{user}": {
      "get": {
        "tags": [],
        "description": "",
        "parameters": [
          {
            "name": "user",
            "in": "path",
            "required": true,
            "type": "string"
          }
        ],
        "responses": {
          "201": {
            "description": "Created"
          },
          "401": {
            "description": "Unauthorized"
          }
        }
      }
    },
    "/city/": {
      "post": {
        "tags": [],
        "description": "",
        "parameters": [],
        "responses": {
          "201": {
            "description": "Created"
          },
          "401": {
            "description": "Unauthorized"
          }
        }
      },
      "get": {
        "tags": [],
        "description": "",
        "parameters": [],
        "responses": {
          "201": {
            "description": "Created"
          },
          "401": {
            "description": "Unauthorized"
          }
        }
      }
    },
    "/city/{city}": {
      "get": {
        "tags": [],
        "description": "",
        "parameters": [
          {
            "name": "city",
            "in": "path",
            "required": true,
            "type": "string"
          }
        ],
        "responses": {
          "201": {
            "description": "Created"
          },
          "401": {
            "description": "Unauthorized"
          }
        }
      }
    },
    "/station/": {
      "post": {
        "tags": [],
        "description": "",
        "parameters": [],
        "responses": {
          "201": {
            "description": "Created"
          },
          "401": {
            "description": "Unauthorized"
          }
        }
      },
      "get": {
        "tags": [],
        "description": "",
        "parameters": [],
        "responses": {
          "201": {
            "description": "Created"
          },
          "401": {
            "description": "Unauthorized"
          }
        }
      }
    },
    "/station/{station}": {
      "get": {
        "tags": [],
        "description": "",
        "parameters": [
          {
            "name": "station",
            "in": "path",
            "required": true,
            "type": "string"
          }
        ],
        "responses": {
          "201": {
            "description": "Created"
          },
          "401": {
            "description": "Unauthorized"
          }
        }
      }
    },
    "/vehicle/": {
      "post": {
        "tags": [],
        "description": "",
        "parameters": [],
        "responses": {
          "201": {
            "description": "Created"
          },
          "401": {
            "description": "Unauthorized"
          }
        }
      },
      "get": {
        "tags": [],
        "description": "",
        "parameters": [],
        "responses": {
          "201": {
            "description": "Created"
          },
          "401": {
            "description": "Unauthorized"
          }
        }
      }
    },
    "/vehicle/{vehicle}": {
      "get": {
        "tags": [],
        "description": "",
        "parameters": [
          {
            "name": "vehicle",
            "in": "path",
            "required": true,
            "type": "string"
          }
        ],
        "responses": {
          "201": {
            "description": "Created"
          },
          "401": {
            "description": "Unauthorized"
          }
        }
      }
    },
    "/element/": {
      "post": {
        "tags": [],
        "description": "",
        "parameters": [],
        "responses": {
          "201": {
            "description": "Created"
          },
          "500": {
            "description": "Internal Server Error"
          }
        }
      },
      "get": {
        "tags": [],
        "description": "",
        "parameters": [],
        "responses": {
          "201": {
            "description": "Created"
          },
          "401": {
            "description": "Unauthorized"
          }
        }
      }
    },
    "/element/{station}": {
      "get": {
        "tags": [],
        "description": "",
        "parameters": [
          {
            "name": "station",
            "in": "path",
            "required": true,
            "type": "string"
          }
        ],
        "responses": {
          "201": {
            "description": "Created"
          },
          "500": {
            "description": "Internal Server Error"
          }
        }
      }
    },
    "/route/": {
      "post": {
        "tags": [],
        "description": "",
        "parameters": [],
        "responses": {
          "201": {
            "description": "Created"
          },
          "401": {
            "description": "Unauthorized"
          }
        }
      },
      "get": {
        "tags": [],
        "description": "",
        "parameters": [],
        "responses": {
          "201": {
            "description": "Created"
          },
          "401": {
            "description": "Unauthorized"
          }
        }
      }
    },
    "/route/works-state/": {
      "get": {
        "tags": [],
        "description": "",
        "parameters": [],
        "responses": {
          "201": {
            "description": "Created"
          },
          "401": {
            "description": "Unauthorized"
          }
        }
      }
    },
    "/route/{user}": {
      "get": {
        "tags": [],
        "description": "",
        "parameters": [
          {
            "name": "user",
            "in": "path",
            "required": true,
            "type": "string"
          }
        ],
        "responses": {
          "201": {
            "description": "Created"
          },
          "401": {
            "description": "Unauthorized"
          }
        }
      }
    },
    "/material/": {
      "post": {
        "tags": [],
        "description": "",
        "parameters": [],
        "responses": {
          "201": {
            "description": "Created"
          },
          "401": {
            "description": "Unauthorized"
          }
        }
      },
      "get": {
        "tags": [],
        "description": "",
        "parameters": [],
        "responses": {
          "201": {
            "description": "Created"
          },
          "401": {
            "description": "Unauthorized"
          }
        }
      }
    },
    "/operation/": {
      "put": {
        "tags": [],
        "description": "",
        "parameters": [],
        "responses": {
          "201": {
            "description": "Created"
          },
          "401": {
            "description": "Unauthorized"
          }
        }
      }
    },
    "/auth/login": {
      "post": {
        "tags": [],
        "description": "",
        "parameters": [],
        "responses": {}
      }
    },
    "/auth/refresh-token/{data}": {
      "post": {
        "tags": [],
        "description": "",
        "parameters": [
          {
            "name": "data",
            "in": "path",
            "required": true,
            "type": "string"
          }
        ],
        "responses": {}
      }
    },
    "/auth/recovery": {
      "post": {
        "tags": [],
        "description": "",
        "parameters": [
          {
            "name": "obj",
            "in": "body",
            "schema": {
              "type": "object",
              "properties": {
                "email": {
                  "example": "any"
                }
              }
            }
          }
        ],
        "responses": {}
      }
    },
    "/auth/change-password": {
      "post": {
        "tags": [],
        "description": "",
        "parameters": [
          {
            "name": "obj",
            "in": "body",
            "schema": {
              "type": "object",
              "properties": {
                "token": {
                  "example": "any"
                },
                "newPassword": {
                  "example": "any"
                }
              }
            }
          }
        ],
        "responses": {}
      }
    }
  },
  "definitions": {}
}